{"index":{"links":{"/":[{"source":"/","target":"/Menu-de-Navega%C3%A7%C3%A3o","text":"Menu de Navegação"}],"/notes/A-fam%C3%ADlia":[{"source":"/notes/A-fam%C3%ADlia","target":"/Menu-de-Navega%C3%A7%C3%A3o","text":"Menu de Navegação"}],"/notes/Entendimento-de-fam%C3%ADlia":[{"source":"/notes/Entendimento-de-fam%C3%ADlia","target":"/Rela%C3%A7%C3%A3o-com-irm%C3%A3s","text":"relação distante com as minhas irmãs"},{"source":"/notes/Entendimento-de-fam%C3%ADlia","target":"/Migra%C3%A7%C3%A3o-lealdade-e-mitos","text":"mito"},{"source":"/notes/Entendimento-de-fam%C3%ADlia","target":"/Menu-de-Navega%C3%A7%C3%A3o","text":"Menu de Navegação"}],"/notes/Menu-de-Navega%C3%A7%C3%A3o":[{"source":"/notes/Menu-de-Navega%C3%A7%C3%A3o","target":"/Motiva%C3%A7%C3%B5es","text":"Motivações"},{"source":"/notes/Menu-de-Navega%C3%A7%C3%A3o","target":"/A-fam%C3%ADlia","text":"A família"},{"source":"/notes/Menu-de-Navega%C3%A7%C3%A3o","target":"/Entendimento-de-fam%C3%ADlia","text":"Entendimento de família"},{"source":"/notes/Menu-de-Navega%C3%A7%C3%A3o","target":"/Rela%C3%A7%C3%A3o-com-irm%C3%A3s","text":"Relação com irmãs"},{"source":"/notes/Menu-de-Navega%C3%A7%C3%A3o","target":"/Morando-longe","text":"Morando longe"},{"source":"/notes/Menu-de-Navega%C3%A7%C3%A3o","target":"/Migra%C3%A7%C3%A3o-lealdade-e-mitos","text":"Migração, lealdade e mitos"},{"source":"/notes/Menu-de-Navega%C3%A7%C3%A3o","target":"/Referencias","text":"Referências"}],"/notes/Migra%C3%A7%C3%A3o-lealdade-e-mitos":[{"source":"/notes/Migra%C3%A7%C3%A3o-lealdade-e-mitos","target":"/Menu-de-Navega%C3%A7%C3%A3o","text":"Menu de navegação"}],"/notes/Morando-longe":[{"source":"/notes/Morando-longe","target":"/Menu-de-Navega%C3%A7%C3%A3o","text":"Menu de Navegação"}],"/notes/Motiva%C3%A7%C3%B5es":[{"source":"/notes/Motiva%C3%A7%C3%B5es","target":"/Entendimento-de-fam%C3%ADlia","text":"definição de família"},{"source":"/notes/Motiva%C3%A7%C3%B5es","target":"/Migra%C3%A7%C3%A3o-lealdade-e-mitos","text":"lealdade e mitos"},{"source":"/notes/Motiva%C3%A7%C3%B5es","target":"/Menu-de-Navega%C3%A7%C3%A3o","text":"Menu de Navegação"}],"/notes/Referencias":[{"source":"/notes/Referencias","target":"/Menu-de-Navega%C3%A7%C3%A3o","text":"Menu de Navegação"}],"/notes/Rela%C3%A7%C3%A3o-com-irm%C3%A3s":[{"source":"/notes/Rela%C3%A7%C3%A3o-com-irm%C3%A3s","target":"/Morando-longe","text":"fui morar com minha irmã mais nova"},{"source":"/notes/Rela%C3%A7%C3%A3o-com-irm%C3%A3s","target":"/Menu-de-Navega%C3%A7%C3%A3o","text":"Menu de navegação"}]},"backlinks":{"/A-fam%C3%ADlia":[{"source":"/notes/Menu-de-Navega%C3%A7%C3%A3o","target":"/A-fam%C3%ADlia","text":"A família"}],"/Entendimento-de-fam%C3%ADlia":[{"source":"/notes/Menu-de-Navega%C3%A7%C3%A3o","target":"/Entendimento-de-fam%C3%ADlia","text":"Entendimento de família"},{"source":"/notes/Motiva%C3%A7%C3%B5es","target":"/Entendimento-de-fam%C3%ADlia","text":"definição de família"}],"/Menu-de-Navega%C3%A7%C3%A3o":[{"source":"/","target":"/Menu-de-Navega%C3%A7%C3%A3o","text":"Menu de Navegação"},{"source":"/notes/A-fam%C3%ADlia","target":"/Menu-de-Navega%C3%A7%C3%A3o","text":"Menu de Navegação"},{"source":"/notes/Entendimento-de-fam%C3%ADlia","target":"/Menu-de-Navega%C3%A7%C3%A3o","text":"Menu de Navegação"},{"source":"/notes/Migra%C3%A7%C3%A3o-lealdade-e-mitos","target":"/Menu-de-Navega%C3%A7%C3%A3o","text":"Menu de navegação"},{"source":"/notes/Morando-longe","target":"/Menu-de-Navega%C3%A7%C3%A3o","text":"Menu de Navegação"},{"source":"/notes/Motiva%C3%A7%C3%B5es","target":"/Menu-de-Navega%C3%A7%C3%A3o","text":"Menu de Navegação"},{"source":"/notes/Referencias","target":"/Menu-de-Navega%C3%A7%C3%A3o","text":"Menu de Navegação"},{"source":"/notes/Rela%C3%A7%C3%A3o-com-irm%C3%A3s","target":"/Menu-de-Navega%C3%A7%C3%A3o","text":"Menu de navegação"}],"/Migra%C3%A7%C3%A3o-lealdade-e-mitos":[{"source":"/notes/Entendimento-de-fam%C3%ADlia","target":"/Migra%C3%A7%C3%A3o-lealdade-e-mitos","text":"mito"},{"source":"/notes/Menu-de-Navega%C3%A7%C3%A3o","target":"/Migra%C3%A7%C3%A3o-lealdade-e-mitos","text":"Migração, lealdade e mitos"},{"source":"/notes/Motiva%C3%A7%C3%B5es","target":"/Migra%C3%A7%C3%A3o-lealdade-e-mitos","text":"lealdade e mitos"}],"/Morando-longe":[{"source":"/notes/Menu-de-Navega%C3%A7%C3%A3o","target":"/Morando-longe","text":"Morando longe"},{"source":"/notes/Rela%C3%A7%C3%A3o-com-irm%C3%A3s","target":"/Morando-longe","text":"fui morar com minha irmã mais nova"}],"/Motiva%C3%A7%C3%B5es":[{"source":"/notes/Menu-de-Navega%C3%A7%C3%A3o","target":"/Motiva%C3%A7%C3%B5es","text":"Motivações"}],"/Referencias":[{"source":"/notes/Menu-de-Navega%C3%A7%C3%A3o","target":"/Referencias","text":"Referências"}],"/Rela%C3%A7%C3%A3o-com-irm%C3%A3s":[{"source":"/notes/Entendimento-de-fam%C3%ADlia","target":"/Rela%C3%A7%C3%A3o-com-irm%C3%A3s","text":"relação distante com as minhas irmãs"},{"source":"/notes/Menu-de-Navega%C3%A7%C3%A3o","target":"/Rela%C3%A7%C3%A3o-com-irm%C3%A3s","text":"Relação com irmãs"}]}},"links":[{"source":"/","target":"/Menu-de-Navega%C3%A7%C3%A3o","text":"Menu de Navegação"},{"source":"/notes/A-fam%C3%ADlia","target":"/Menu-de-Navega%C3%A7%C3%A3o","text":"Menu de Navegação"},{"source":"/notes/Entendimento-de-fam%C3%ADlia","target":"/Rela%C3%A7%C3%A3o-com-irm%C3%A3s","text":"relação distante com as minhas irmãs"},{"source":"/notes/Entendimento-de-fam%C3%ADlia","target":"/Migra%C3%A7%C3%A3o-lealdade-e-mitos","text":"mito"},{"source":"/notes/Entendimento-de-fam%C3%ADlia","target":"/Menu-de-Navega%C3%A7%C3%A3o","text":"Menu de Navegação"},{"source":"/notes/Menu-de-Navega%C3%A7%C3%A3o","target":"/Motiva%C3%A7%C3%B5es","text":"Motivações"},{"source":"/notes/Menu-de-Navega%C3%A7%C3%A3o","target":"/A-fam%C3%ADlia","text":"A família"},{"source":"/notes/Menu-de-Navega%C3%A7%C3%A3o","target":"/Entendimento-de-fam%C3%ADlia","text":"Entendimento de família"},{"source":"/notes/Menu-de-Navega%C3%A7%C3%A3o","target":"/Rela%C3%A7%C3%A3o-com-irm%C3%A3s","text":"Relação com irmãs"},{"source":"/notes/Menu-de-Navega%C3%A7%C3%A3o","target":"/Morando-longe","text":"Morando longe"},{"source":"/notes/Menu-de-Navega%C3%A7%C3%A3o","target":"/Migra%C3%A7%C3%A3o-lealdade-e-mitos","text":"Migração, lealdade e mitos"},{"source":"/notes/Menu-de-Navega%C3%A7%C3%A3o","target":"/Referencias","text":"Referências"},{"source":"/notes/Migra%C3%A7%C3%A3o-lealdade-e-mitos","target":"/Menu-de-Navega%C3%A7%C3%A3o","text":"Menu de navegação"},{"source":"/notes/Morando-longe","target":"/Menu-de-Navega%C3%A7%C3%A3o","text":"Menu de Navegação"},{"source":"/notes/Motiva%C3%A7%C3%B5es","target":"/Entendimento-de-fam%C3%ADlia","text":"definição de família"},{"source":"/notes/Motiva%C3%A7%C3%B5es","target":"/Migra%C3%A7%C3%A3o-lealdade-e-mitos","text":"lealdade e mitos"},{"source":"/notes/Motiva%C3%A7%C3%B5es","target":"/Menu-de-Navega%C3%A7%C3%A3o","text":"Menu de Navegação"},{"source":"/notes/Referencias","target":"/Menu-de-Navega%C3%A7%C3%A3o","text":"Menu de Navegação"},{"source":"/notes/Rela%C3%A7%C3%A3o-com-irm%C3%A3s","target":"/Morando-longe","text":"fui morar com minha irmã mais nova"},{"source":"/notes/Rela%C3%A7%C3%A3o-com-irm%C3%A3s","target":"/Menu-de-Navega%C3%A7%C3%A3o","text":"Menu de navegação"}]}